cctrial/__init__.py
cctrial/cctrial.py
cctrial/freedesktop.py
cctrial/notify.py
cctrial/osx.py
cctrial/reporter.py
cctrial/runner.py
cctrial/smart.py
cctrial/watcher.py
cctrial-1.2.7.dist-info/DESCRIPTION.rst
cctrial-1.2.7.dist-info/METADATA
cctrial-1.2.7.dist-info/RECORD
cctrial-1.2.7.dist-info/WHEEL
cctrial-1.2.7.dist-info/entry_points.txt
cctrial-1.2.7.dist-info/metadata.json
cctrial-1.2.7.dist-info/top_level.txt
