Metadata-Version: 2.0
Name: cctrial
Version: 1.2.7
Summary: continous trial runner
Home-page: UNKNOWN
Author: Pierre Tardy
Author-email: tardyp@gmail.com
License: MIT
Platform: UNKNOWN
Requires-Dist: argh
Requires-Dist: twisted (>=15.0.0)
Requires-Dist: watchdog
